main.py
my_math.py
test_my_math.py
testCICD-0.1.dist-info/METADATA
testCICD-0.1.dist-info/WHEEL
testCICD-0.1.dist-info/top_level.txt
testCICD-0.1.dist-info/RECORD
