Metadata-Version: 2.1
Name: testCICD
Version: 0.1
Summary: A sample Python package to test CI/CD
Author: Angelo Ferrando
Author-email: angelo.ferrando42@gmail.com
